Metadata-Version: 2.1
Name: FastHubPy
Version: 0.1
Summary: Utilizes the TTS service from Fasthub.net
Home-page: 
Download-URL: https://github.com/OmegasGithub/FastHubPy/archive/refs/tags/v_01.tar.gz
Author: Me
Author-email: 
License: MIT
Keywords: tts,fasthub,text to speech
Classifier: Development Status :: 5 - Production/Stable
Classifier: Intended Audience :: Developers
Classifier: Topic :: Software Development
Classifier: License :: OSI Approved :: MIT License
Classifier: Programming Language :: Python :: 3.11
License-File: LICENSE.txt
